modelscope_image_gen_mcp/__init__.py
modelscope_image_gen_mcp/__main__.py
modelscope_image_gen_mcp/server.py
modelscope_image_gen_mcp-0.1.4.dist-info/METADATA
modelscope_image_gen_mcp-0.1.4.dist-info/WHEEL
modelscope_image_gen_mcp-0.1.4.dist-info/entry_points.txt
modelscope_image_gen_mcp-0.1.4.dist-info/RECORD
