Metadata-Version: 2.4
Name: modelscope_image_gen_mcp
Version: 0.1.4
Summary: A Model Context Protocol (MCP) server to generate images by text prompts via modelscope
Author-email: Zhiling Luo <godot.lzl@alibaba-inc.com>
Requires-Python: >=3.11
Requires-Dist: mcp>=1.0.0
Requires-Dist: requests
